spectralinvariant/__init__.py
spectralinvariant/hypdatatools_algorithms.py
spectralinvariant/hypdatatools_img.py
spectralinvariant/hypdatatools_utils.py
spectralinvariant/prospect.py
spectralinvariant/spectralinvariants.py
spectralinvariant-0.0.1.dist-info/LICENSE
spectralinvariant-0.0.1.dist-info/METADATA
spectralinvariant-0.0.1.dist-info/WHEEL
spectralinvariant-0.0.1.dist-info/top_level.txt
spectralinvariant-0.0.1.dist-info/RECORD
