Metadata-Version: 2.1
Name: spectralinvariant
Version: 0.0.1
Summary: Spectral invariants package
Home-page: https://github.com/mottus/spectralinvariant
Author: Author Name
Author-email: author.name@adress.com
License: UNKNOWN
Platform: UNKNOWN
Classifier: Programming Language :: Python :: 3
Classifier: License :: OSI Approved :: GNU General Public License v3 (GPLv3)
Classifier: Operating System :: OS Independent
Requires-Python: >=3.6
